[
    {
        "label": "AIR HANGAT",
        "value": "AIR HANGAT"
    },
    {
        "label": "DANAU KERINCI",
        "value": "DANAU KERINCI"
    },
    {
        "label": "AIR HANGAT TIMUR",
        "value": "AIR HANGAT TIMUR"
    },
    {
        "label": "BATANG MERANGIN",
        "value": "BATANG MERANGIN"
    },
    {
        "label": "BUKIT KERMAN",
        "value": "BUKIT KERMAN"
    },
    {
        "label": "DEPATI PELAYO",
        "value": "DEPATI PELAYO"
    },
    {
        "label": "GUNUNG KERINCI",
        "value": "GUNUNG KERINCI"
    },
    {
        "label": "GUNUNG RAYA",
        "value": "GUNUNG RAYA"
    },
    {
        "label": "GUNUNG TUJUH",
        "value": "GUNUNG TUJUH"
    },
    {
        "label": "KAYU ARO",
        "value": "KAYU ARO"
    },
    {
        "label": "BUKITKERMAN",
        "value": "BUKITKERMAN"
    },
    {
        "label": "KAYU ARO BARAT",
        "value": "KAYU ARO BARAT"
    },
    {
        "label": "KELILING DANAU",
        "value": "KELILING DANAU"
    },
    {
        "label": "SITINJAU LAUT",
        "value": "SITINJAU LAUT"
    },
    {
        "label": "SIULAK",
        "value": "SIULAK"
    },
    {
        "label": "SIULAK MUKAI",
        "value": "SIULAK MUKAI"
    }
]