[
    {
        "label": "AIR BERUNDANG",
        "value": "AIR BERUNDANG"
    },
    {
        "label": "AIR PINANG",
        "value": "AIR PINANG"
    },
    {
        "label": "PANTON LUAS",
        "value": "PANTON LUAS"
    },
    {
        "label": "PASAR",
        "value": "PASAR"
    },
    {
        "label": "PANJUPIAN",
        "value": "PANJUPIAN"
    },
    {
        "label": "PADANG",
        "value": "PADANG"
    },
    {
        "label": "LHOK RUKAM",
        "value": "LHOK RUKAM"
    },
    {
        "label": "LHOK KEUTAPANG",
        "value": "LHOK KEUTAPANG"
    },
    {
        "label": "LHOK BENGKUANG",
        "value": "LHOK BENGKUANG"
    },
    {
        "label": "LHOK BENGKUANG TIMUR",
        "value": "LHOK BENGKUANG TIMUR"
    },
    {
        "label": "JAMBO APHA",
        "value": "JAMBO APHA"
    },
    {
        "label": "HULU",
        "value": "HULU"
    },
    {
        "label": "GUNUNG KERAMBIL",
        "value": "GUNUNG KERAMBIL"
    },
    {
        "label": "HILIR",
        "value": "HILIR"
    },
    {
        "label": "TEPI AIR",
        "value": "TEPI AIR"
    },
    {
        "label": "BATU ITAM",
        "value": "BATU ITAM"
    }
]
