[
    {
        "label": "TEGALDLIMO",
        "value": "TEGALDLIMO"
    },
    {
        "label": "MUNCAR",
        "value": "MUNCAR"
    },
    {
        "label": "GAMBIRAN",
        "value": "GAMBIRAN"
    },
    {
        "label": "SRONO",
        "value": "SRONO"
    },
    {
        "label": "WONGSOREJO",
        "value": "WONGSOREJO"
    },
    {
        "label": "BLIMBINGSARI",
        "value": "BLIMBINGSARI"
    },
    {
        "label": "BANYUWANGI",
        "value": "BANYUWANGI"
    },
    {
        "label": "GLENMORE",
        "value": "GLENMORE"
    },
    {
        "label": "SEMPU",
        "value": "SEMPU"
    },
    {
        "label": "BANGOREJO",
        "value": "BANGOREJO"
    },
    {
        "label": "KALIPURO",
        "value": "KALIPURO"
    },
    {
        "label": "TEGALSARI",
        "value": "TEGALSARI"
    },
    {
        "label": "CLURING",
        "value": "CLURING"
    },
    {
        "label": "KABAT",
        "value": "KABAT"
    },
    {
        "label": "LICIN",
        "value": "LICIN"
    },
    {
        "label": "GLAGAH",
        "value": "GLAGAH"
    },
    {
        "label": "PURWOHARJO",
        "value": "PURWOHARJO"
    },
    {
        "label": "PESANGGARAN",
        "value": "PESANGGARAN"
    },
    {
        "label": "SONGGON",
        "value": "SONGGON"
    },
    {
        "label": "SINGOJURUH",
        "value": "SINGOJURUH"
    },
    {
        "label": "SILIRAGUNG",
        "value": "SILIRAGUNG"
    },
    {
        "label": "GENTENG",
        "value": "GENTENG"
    },
    {
        "label": "ROGOJAMPI",
        "value": "ROGOJAMPI"
    },
    {
        "label": "GIRI",
        "value": "GIRI"
    },
    {
        "label": "KALIBARU",
        "value": "KALIBARU"
    }
]
