[
    {
        "label":"LAWES ALAS",
        "value":"LAWES ALAS"
    },
    {
        "label":"LAWES SIGALA-GALA",
        "value":"LAWES SIGALA-GALA"
    },
    {
        "label":"BAMBEL",
        "value":"BAMBEL"
    },
    {
        "label":"BABUSSALAM",
        "value":"BABUSSALAM"
    },
    {
        "label":"BADAR",
        "value":"BADAR"
    },
    {
        "label":"BABUL MAKMUR",
        "value":"BABUK MAKMUR"
    },
    {
        "label":"DARUL HASANAH",
        "value":"DARUL HASANAH"
    },
    {
        "label":"LAWE BULAN",
        "value":"LAWE BULAN"
    },
    {
        "label":"BUKIT TUSAM",
        "value":"BUKIT TUSAM"
    },
    {
        "label":"SEMADAM",
        "value":"SEMADAM"
    },
    {
        "label":"BABUL RAHMAH",
        "value":"BABUL RAHMAH"
    },
    {
        "label":"KETAMBE",
        "value":"KETAMBE"
    },
    {
        "label":"DELENG POKHKISEN",
        "value":"DELENG POKHKISEN"
    },
    {
        "label":"LAWE SUMUR",
        "value":"LAWE SUMUR"
    },
    {
        "label":"TANOH ALAS",
        "value":"TANOH ALAS"
    },
    {
        "label":"LEUSER",
        "value":"LEUSER"
    }
]