[
    {
        "label": "PUUK",
        "value": "PUUK"
    },
    {
        "label": "RABEU",
        "value": "RABEU"
    },
    {
        "label": "UJONG BLANG",
        "value": "UJONG BLANG"
    },
    {
        "label": "MEUNASAH BAK TRIENG",
        "value": "MEUNASAH BAK TRIENG"
    },
    {
        "label": "TUMPOK LAMPOH",
        "value": "TUMPOK LAMPOH"
    },
    {
        "label": "LEUPUNG MESJID",
        "value": "LEUPUNG MESJID"
    },
    {
        "label": "LEUPUNG ULE ALUE",
        "value": "LEUPUNG ULE ALUE"
    },
    {
        "label": "LAMTEUBE GEUPULA",
        "value": "LAMTEUBE GEUPULA"
    },
    {
        "label": "LAMTEUBE MON ARA",
        "value": "LAMTEUBE MON ARA"
    },
    {
        "label": "LAMPOH KEUDE",
        "value": "LAMPOH KEUDE"
    },
    {
        "label": "LAMPOH TAROM",
        "value": "LAMPOH TAROM"
    },
    {
        "label": "LAMBRO BILEU",
        "value": "LAMBRO BILEU"
    },
    {
        "label": "LAMBRO DEYAH",
        "value": "LAMBRO DEYAH"
    },
    {
        "label": "LAMCEU",
        "value": "LAMCEU"
    },
    {
        "label": "LAM SABANG",
        "value": "LAM SABANG"
    },
    {
        "label": "LAM SEUNONG",
        "value": "LAM SEUNONG"
    },
    {
        "label": "LAM TRIENG",
        "value": "LAM TRIENG"
    },
    {
        "label": "LAM NEUHEUN",
        "value": "LAM NEUHEUN"
    },
    {
        "label": "LAM PUUK",
        "value": "LAM PUUK"
    },
    {
        "label": "LAM RAYA",
        "value": "LAM RAYA"
    },
    {
        "label": "LAM ROH",
        "value": "LAM ROH"
    },
    {
        "label": "LAM BAED",
        "value": "LAM BAED"
    },
    {
        "label": "LAM BUNOT PAYA",
        "value": "LAM BUNOT PAYA"
    },
    {
        "label": "LAM BUNOT TANOH",
        "value": "LAM BUNOT TANOH"
    },
    {
        "label": "LAM GLUMPANG/GEULUMPANG",
        "value": "LAM GLUMPANG/GEULUMPANG"
    },
    {
        "label": "LAM ALUE CUT",
        "value": "LAM ALUE CUT"
    },
    {
        "label": "LAM ALUE RAYA",
        "value": "LAM ALUE RAYA"
    },
    {
        "label": "LAM ASAN",
        "value": "LAM ASAN"
    },
    {
        "label": "KRUENG ANOI",
        "value": "KRUENG ANOI"
    },
    {
        "label": "GUE",
        "value": "GUE"
    },
    {
        "label": "DEYAH",
        "value": "DEYAH"
    },
    {
        "label": "COT YANG",
        "value": "COT YANG"
    },
    {
        "label": "CUCUM",
        "value": "CUCUM"
    },
    {
        "label": "COT PEUTANO",
        "value": "COT PEUTANO"
    },
    {
        "label": "COT PREH",
        "value": "COT PREH"
    },
    {
        "label": "COT RAYA",
        "value": "COT RAYA"
    },
    {
        "label": "COT MASAM",
        "value": "COT MASAM"
    },
    {
        "label": "COT LAMEE",
        "value": "COT LAMEE"
    },
    {
        "label": "COT MANCANG",
        "value": "COT MANCANG"
    },
    {
        "label": "COT BEUT",
        "value": "COT BEUT"
    },
    {
        "label": "COT CUT",
        "value": "COT CUT"
    },
    {
        "label": "BUENG BAKJOK",
        "value": "BUENG BAKJOK"
    },
    {
        "label": "BEURANGONG",
        "value": "BEURANGONG"
    },
    {
        "label": "BABAH JURONG",
        "value": "BABAH JURONG"
    },
    {
        "label": "BAK BULOH",
        "value": "BAK BULOH"
    },
    {
        "label": "ARON",
        "value": "ARON"
    },
    {
        "label": "SEUPEU",
        "value": "SEUPEU"
    }
]